GPyM_TM/GPM.py
GPyM_TM/GSDMM.py
GPyM_TM/__init__.py
GPyM_TM-3.0.1.dist-info/LICENSE.txt
GPyM_TM-3.0.1.dist-info/METADATA
GPyM_TM-3.0.1.dist-info/WHEEL
GPyM_TM-3.0.1.dist-info/top_level.txt
GPyM_TM-3.0.1.dist-info/RECORD
