Metadata-Version: 2.1
Name: GPyM-TM
Version: 3.0.1
Summary: The following package enables users to perform text modelling
Home-page: https://github.com/jrmazarura/GPM
Author: Jocelyn Mazarura
Author-email: <jocelyn.mazarura@up.ac.za>
License: UNKNOWN
Platform: UNKNOWN
Classifier: Programming Language :: Python :: 3
Classifier: License :: OSI Approved :: MIT License
Classifier: Operating System :: OS Independent
Requires-Python: >=3.6
